activecampaign/__init__.py
activecampaign/client.py
activecampaign/contacts.py
activecampaign/exceptions.py
activecampaign/http.py
activecampaign-0.2.0.dist-info/AUTHORS.rst
activecampaign-0.2.0.dist-info/LICENSE
activecampaign-0.2.0.dist-info/METADATA
activecampaign-0.2.0.dist-info/WHEEL
activecampaign-0.2.0.dist-info/top_level.txt
activecampaign-0.2.0.dist-info/RECORD
