Metadata-Version: 2.1
Name: activecampaign
Version: 0.2.0
Summary: ActiveCampaign API client
Home-page: https://github.com/bennylope/activecampaign
Author: Ben Lopatin
Author-email: ben@benlopatin.com
License: BSD
Keywords: activecampaign
Platform: UNKNOWN
Classifier: Development Status :: 2 - Pre-Alpha
Classifier: Intended Audience :: Developers
Classifier: License :: OSI Approved :: BSD License
Classifier: Natural Language :: English
Classifier: Programming Language :: Python :: 3
Classifier: Programming Language :: Python :: 3.6
Classifier: Programming Language :: Python :: 3.7
Requires-Dist: requests
